recapturedocs/__init__.py
recapturedocs/agency.py
recapturedocs/aws.py
recapturedocs/config.py
recapturedocs/dropbox.py
recapturedocs/errors.py
recapturedocs/jsonpickle.py
recapturedocs/model.py
recapturedocs/persistence.py
recapturedocs/prod.conf
recapturedocs/server.py
recapturedocs/staging.conf
recapturedocs/unittest.conf
recapturedocs/media/banner.psd
recapturedocs/media/draft.pdn
recapturedocs/static/Lorem ipsum.pdf
recapturedocs/static/jquery.blockUI.js
recapturedocs/static/loader.gif
recapturedocs/static/logo.jpg
recapturedocs/static/logo.png
recapturedocs/static/main.js
recapturedocs/static/process.png
recapturedocs/static/sample.pdf
recapturedocs/static/styling/arrow.png
recapturedocs/static/styling/bnt.png
recapturedocs/static/styling/body_bg.jpg
recapturedocs/static/styling/close-button.png
recapturedocs/static/styling/foote_bg.png
recapturedocs/static/styling/get_started_bg.png
recapturedocs/static/styling/icon.png
recapturedocs/static/styling/input_bg.png
recapturedocs/static/styling/logo_bg.png
recapturedocs/static/styling/main.css
recapturedocs/static/styling/master.css
recapturedocs/static/styling/menu_bg.png
recapturedocs/static/styling/menu_left-bg.jpg
recapturedocs/static/styling/menu_right_line.jpg
recapturedocs/static/styling/mid_left_bg.jpg
recapturedocs/static/styling/red_line.jpg
recapturedocs/text/about.rst
recapturedocs/text/completed features.rst
recapturedocs/text/contact us.rst
recapturedocs/text/design ad.rst
recapturedocs/text/privacy.rst
recapturedocs/text/support.rst
recapturedocs/text/terms.rst
recapturedocs/text/work in progress.rst
recapturedocs/view/declined.xhtml
recapturedocs/view/design goals.xhtml
recapturedocs/view/main.xhtml
recapturedocs/view/master.xhtml
recapturedocs/view/menu.xhtml
recapturedocs/view/retype page.xhtml
recapturedocs/view/simple.xhtml
recapturedocs/view/status.xhtml
recapturedocs/view/admin/status.xhtml
recapturedocs/view/ggc/list.xhtml
ubuntu/nginx config
ubuntu/recapturedocs.service
recapturedocs-5.0.2.dist-info/LICENSE
recapturedocs-5.0.2.dist-info/METADATA
recapturedocs-5.0.2.dist-info/WHEEL
recapturedocs-5.0.2.dist-info/entry_points.txt
recapturedocs-5.0.2.dist-info/top_level.txt
recapturedocs-5.0.2.dist-info/RECORD
