Metadata-Version: 2.1
Name: recapturedocs
Version: 5.0.2
Summary: Library for RecaptureDocs.com
Home-page: https://github.com/jaraco/recapturedocs
Author: Jason R. Coombs
Author-email: jaraco@jaraco.com
Classifier: Development Status :: 5 - Production/Stable
Classifier: Intended Audience :: Developers
Classifier: License :: OSI Approved :: MIT License
Classifier: Programming Language :: Python :: 3
Classifier: Programming Language :: Python :: 3 :: Only
Requires-Python: >=3.8
License-File: LICENSE
Requires-Dist: cherrypy >=3.2.3
Requires-Dist: genshi >=0.6
Requires-Dist: boto3
Requires-Dist: PyPDF2
Requires-Dist: keyring >=0.7.1
Requires-Dist: path
Requires-Dist: docutils
Requires-Dist: jaraco.modb >=3.2
Requires-Dist: pymongo >=1.9
Requires-Dist: httpagentparser >=1.0.1
Requires-Dist: dropbox >=1.5
Requires-Dist: newrelic
Requires-Dist: jaraco.text
Requires-Dist: jaraco.itertools
Requires-Dist: jaraco.logging
Requires-Dist: jaraco.collections
Requires-Dist: jaraco.classes
Requires-Dist: jaraco.functools >=1.2
Requires-Dist: jaraco.email
Requires-Dist: jaraco.mongodb
Provides-Extra: docs
Requires-Dist: sphinx >=3.5 ; extra == 'docs'
Requires-Dist: sphinx <7.2.5 ; extra == 'docs'
Requires-Dist: jaraco.packaging >=9.3 ; extra == 'docs'
Requires-Dist: rst.linker >=1.9 ; extra == 'docs'
Requires-Dist: furo ; extra == 'docs'
Requires-Dist: sphinx-lint ; extra == 'docs'
Provides-Extra: testing
Requires-Dist: pytest >=6 ; extra == 'testing'
Requires-Dist: pytest-checkdocs >=2.4 ; extra == 'testing'
Requires-Dist: pytest-cov ; extra == 'testing'
Requires-Dist: pytest-enabler >=2.2 ; extra == 'testing'
Requires-Dist: pytest-ruff ; extra == 'testing'
Requires-Dist: importlib-resources >=1.1 ; extra == 'testing'
Requires-Dist: mock ; extra == 'testing'
Requires-Dist: fabric ; extra == 'testing'
Requires-Dist: jaraco.fabric ; extra == 'testing'
Requires-Dist: keyring ; extra == 'testing'
Requires-Dist: types-requests ; extra == 'testing'
Requires-Dist: types-boto ; extra == 'testing'
Requires-Dist: types-docutils ; extra == 'testing'
Requires-Dist: types-setuptools ; extra == 'testing'
Requires-Dist: types-mock ; extra == 'testing'
Requires-Dist: pytest-black >=0.3.7 ; (platform_python_implementation != "PyPy") and extra == 'testing'
Requires-Dist: pytest-mypy >=0.9.1 ; (platform_python_implementation != "PyPy") and extra == 'testing'
